inputconditioner.v
//------------------------------------------------------------------------
// Input Conditioner
//    1) Synchronizes input to clock domain
//    2) Debounces input
//    3) Creates pulses at edge transitions
//------------------------------------------------------------------------

module inputconditioner
(
input 	    clk,            // Clock domain to synchronize input to
input	    noisysignal,    // (Potentially) noisy input signal
output reg  conditioned,    // Conditioned output signal
output reg  positiveedge,   // 1 clk pulse at rising edge of conditioned
output reg  negativeedge    // 1 clk pulse at falling edge of conditioned
);

    parameter counterwidth = 3; // Counter size, in bits, >= log2(waittime)
    parameter waittime = 3;     // Debounce delay, in clock cycles

    reg[counterwidth-1:0] counter = 0;
    reg synchronizer0 = 0;
    reg synchronizer1 = 0;

    always @(posedge clk ) begin
        if(conditioned == synchronizer1) begin
            counter <= 0;
            positiveedge <= 0;
            negativeedge <= 0;
        end
        else begin
            if( counter == waittime) begin
                counter <= 0;
                conditioned <= synchronizer1;
                positiveedge <= !conditioned & synchronizer1;
                negativeedge <= conditioned & !synchronizer1;
            end
            else
                counter <= counter+1;
        end
        synchronizer0 <= noisysignal; // current signal read at the pos edge of clock
        synchronizer1 <= synchronizer0; // previous signal from the last clock cycle
    end
endmodule

inputconditioner.t.v
//------------------------------------------------------------------------
// Input Conditioner test bench
//------------------------------------------------------------------------

`include "inputconditioner.v"

module testConditioner();

    reg clk;
    reg pin;
    wire conditioned;
    wire rising;
    wire falling;
    
    inputconditioner dut(.clk(clk),
    			 .noisysignal(pin),
			 .conditioned(conditioned),
			 .positiveedge(rising),
			 .negativeedge(falling));

    // Generate clock (50MHz)
    initial clk=0;
    always #10 clk=!clk;    // 50MHz Clock

    reg [49:0] signal;
    reg [49:0] conditioned_output;
    reg [49:0] conditioned_posedge;
    reg [49:0] conditioned_negedge;
    reg [49:0] expected_output;
    reg [49:0] expected_posedge;
    reg [49:0] expected_negedge;
    integer i;
   
    initial begin
    // Your Test Code
    // Be sure to test each of the three conditioner functions:
    // Synchronization, Debouncing, Edge Detection

    $dumpfile("inputconditioner.vcd");
    $dumpvars();
    $display("----------------------------------------");
    $display("Test: Synchronization and Edge Detection");
    $display("----------------------------------------");   

       signal           <= 50'b00000000001111111111000000000011111111110000000000;
       expected_output  <= 50'bxxxxxxxx000000000000001111111111000000000011111111;
       expected_posedge <= 50'bxxxxxxxx000000000000001100000000000000000011000000;
       expected_negedge <= 50'bxxxxxxxxxx0000000000000000000000110000000000000000;
       
       for (i = 0; i < 50; i = i + 1) begin
	  pin <= signal[i];
	  conditioned_output[49-i] <= conditioned;
	  conditioned_posedge[49-i] <= rising;
	  conditioned_negedge[49-i] <= falling;
	  #10;
       end

    $display("Original Signal:     %b", signal);
    $display("Conditioned Output:  %b", conditioned_output);
    $display("Expected Output:     %b", expected_output);
    $display("Conditioned Posedge: %b", conditioned_posedge);
    $display("Expected Posedge:    %b", expected_posedge);
    $display("Conditioned Negedge: %b", conditioned_negedge);
    $display("Expected Negedge:    %b", expected_negedge);

    $display("----------------------------------------");
    $display("Test: Debouncing");
    $display("----------------------------------------");
       
       signal           <= 50'b00000001001111111111000000000011111111110010000000;
       expected_output  <= 50'bxxxxxxxx000000000000001111111111000000000011111111;
       expected_posedge <= 50'bxxxxxxxx000000000000001100000000000000000011000000;
       expected_negedge <= 50'bxxxxxxxxxx0000000000000000000000110000000000000000;
       
       for (i = 0; i < 50; i = i + 1) begin
	  pin <= signal[i];
	  conditioned_output[49-i] <= conditioned;
	  conditioned_posedge[49-i] <= rising;
	  conditioned_negedge[49-i] <= falling;
	  #10;
       end

    $display("Original Signal:     %b", signal);
    $display("Conditioned Output:  %b", conditioned_output);
    $display("Expected Output:     %b", expected_output);
    $display("Conditioned Posedge: %b", conditioned_posedge);
    $display("Expected Posedge:    %b", expected_posedge);
    $display("Conditioned Negedge: %b", conditioned_negedge);
    $display("Expected Negedge:    %b", expected_negedge);    

    $finish;
    end // initial begin
endmodule

inputconditioner.vcd
$date
	Fri Oct 28 14:15:19 2016
$end
$version
	Icarus Verilog
$end
$timescale
	1s
$end
$scope module testConditioner $end
$scope module dut $end
$var wire 1 ! clk $end
$var wire 1 " noisysignal $end
$var reg 1 # conditioned $end
$var reg 3 $ counter [2:0] $end
$var reg 1 % negativeedge $end
$var reg 1 & positiveedge $end
$var reg 1 ' synchronizer0 $end
$var reg 1 ( synchronizer1 $end
$upscope $end
$upscope $end
$enddefinitions $end
#0
$dumpvars
0(
0'
0&
0%
b1 $
0#
0"
1!
$end
#5
1"
#10
0"
0!
#15
1"
#20
b0 $
0"
1!
#30
0!
#40
1!
#50
0!
#60
1'
1!
1"
#70
0!
#80
1(
1!
#90
0!
#100
b1 $
1!
#110
0!
#120
b10 $
1!
#130
0!
#140
b11 $
1!
#150
0!
#160
1&
1#
b0 $
1!
#170
0!
#180
0&
1!
