inputconditioner.v
//------------------------------------------------------------------------
// Input Conditioner
//    1) Synchronizes input to clock domain
//    2) Debounces input
//    3) Creates pulses at edge transitions
//------------------------------------------------------------------------

module inputconditioner
(
input 	    clk,            // Clock domain to synchronize input to
input	    noisysignal,    // (Potentially) noisy input signal
output reg  conditioned,    // Conditioned output signal
output reg  positiveedge,   // 1 clk pulse at rising edge of conditioned
output reg  negativeedge    // 1 clk pulse at falling edge of conditioned
);

    parameter counterwidth = 3; // Counter size, in bits, >= log2(waittime)
    parameter waittime = 3;     // Debounce delay, in clock cycles

    reg[counterwidth-1:0] counter = 0;
    reg synchronizer0 = 0;
    reg synchronizer1 = 0;

    always @(posedge clk ) begin
        if(conditioned == synchronizer1) begin
            counter <= 0;
            positiveedge <= 0;
            negativeedge <= 0;
        end
        else begin
            if( counter == waittime) begin
                counter <= 0;
                conditioned <= synchronizer1;
                positiveedge <= !conditioned & synchronizer1;
                negativeedge <= conditioned & !synchronizer1;
            end
            else
                counter <= counter+1;
        end
        synchronizer0 <= noisysignal; // current signal read at the pos edge of clock
        synchronizer1 <= synchronizer0; // previous signal from the last clock cycle
    end
endmodule

inputconditioner.t.v
//------------------------------------------------------------------------
// Input Conditioner test bench
//------------------------------------------------------------------------
`include "inputconditioner.v"
module testConditioner();

    reg clk;
    reg pin;
    wire conditioned;
    wire rising;
    wire falling;
    integer i;
    inputconditioner dut(.clk(clk),
    			 .noisysignal(pin),
			 .conditioned(conditioned),
			 .positiveedge(rising),
			 .negativeedge(falling));


    // Generate clock (50MHz)
    initial clk=1;
    always #10 clk=!clk;    // 50MHz Clock

    initial begin

    $dumpfile("inputconditioner.vcd");
    $dumpvars(0, dut);
    // Your Test Code
    // Be sure to test each of the three conditioner functions:
    // Synchronize, Clean, Preprocess (edge finding)
    $display("Clock Pin | Conditioned Rising Falling");
    //check a noisy signal
    //1 clock cycle
    pin = 0;  #5; pin = 1; #5; pin = 0;  #5; pin = 1; #5;
    $display("%b   %b | %b   %b   %b", clk, pin, conditioned, rising, falling);
    $display($time);
    //off then on
    //4 clock cycles
    pin = 0;  #40; pin = 1; #40;
    $display("%b   %b | %b   %b   %b", clk, pin, conditioned, rising, falling);
    $display($time);
    //on then off
    //4 clock cycles
    pin = 1;  #4000; pin = 0; #400;
    $display("%b   %b | %b   %b   %b", clk, pin, conditioned, rising, falling);
    $display($time);
    #1000
    $finish;
end

endmodule

inputconditioner.vcd
$date
	Wed Oct 26 20:11:02 2016
$end
$version
	Icarus Verilog
$end
$timescale
	1s
$end
$scope module testConditioner $end
$scope module dut $end
$var wire 1 ! clk $end
$var wire 1 " noisysignal $end
$var reg 1 # conditioned $end
$var reg 5 $ counter [4:0] $end
$var reg 1 % negativeedge $end
$var reg 1 & positiveedge $end
$var reg 1 ' synchronizer0 $end
$var reg 1 ( synchronizer1 $end
$upscope $end
$upscope $end
$enddefinitions $end
#0
$dumpvars
0(
0'
0&
0%
b1 $
0#
0"
1!
$end
#5
1"
#10
0"
0!
#15
1"
#20
b0 $
0"
1!
#30
0!
#40
1!
#50
0!
#60
1'
1!
1"
#70
0!
#80
1(
1!
#90
0!
#100
b1 $
1!
#110
0!
#120
b10 $
1!
#130
0!
#140
b11 $
1!
#150
0!
#160
b100 $
1!
#170
0!
#180
b101 $
1!
#190
0!
#200
b110 $
1!
#210
0!
#220
b111 $
1!
#230
0!
#240
b1000 $
1!
#250
0!
#260
b1001 $
1!
#270
0!
#280
b1010 $
1!
#290
0!
#300
1&
1#
b0 $
1!
#310
0!
#320
0&
1!
